{
  "data": {
    "startData": {},
    "resultData": {
      "runData": {
        "Start": [
          {
            "hints": [],
            "startTime": 1734618352523,
            "executionTime": 0,
            "source": [],
            "executionStatus": "success",
            "data": {
              "main": [
                [
                  {
                    "json": {},
                    "pairedItem": {
                      "item": 0
                    }
                  }
                ]
              ]
            }
          }
        ],
        "Mailchimp1": [
          {
            "hints": [],
            "startTime": 1734618352523,
            "executionTime": 1873,
            "source": [
              {
                "previousNode": "Start"
              }
            ],
            "executionStatus": "success",
            "data": {
              "main": [
                [
                  {
                    "json": {
                      "id": "c81277605b129fdafaacede5ae34e07c",
                      "email_address": "nodeqa@n8n.io",
                      "unique_email_id": "cb7624ba4b",
                      "contact_id": "2f4ff7f445018adb50969f99df88dd9e",
                      "full_name": "node qa",
                      "web_id": 502612022,
                      "email_type": "html",
                      "status": "subscribed",
                      "consents_to_one_to_one_messaging": true,
                      "sms_phone_number": "",
                      "sms_subscription_status": "",
                      "sms_subscription_last_updated": "",
                      "merge_fields": {
                        "object": true
                      },
                      "interests": {
                        "object": true
                      },
                      "stats": {
                        "object": true
                      },
                      "ip_signup": "",
                      "timestamp_signup": "",
                      "ip_opt": "41.62.62.149",
                      "timestamp_opt": "2021-02-19T10:59:04+00:00",
                      "member_rating": 2,
                      "last_changed": "2024-12-19T14:21:21+00:00",
                      "language": "",
                      "vip": false,
                      "email_client": "",
                      "location": {
                        "object": true
                      },
                      "source": "Admin Add",
                      "tags_count": 0,
                      "tags": [
                        "json array"
                      ],
                      "list_id": "eb9ad4be19",
                      "_links": [
                        "json array"
                      ]
                    },
                    "pairedItem": {
                      "item": 0
                    }
                  }
                ]
              ]
            }
          }
        ],
        "Function": [
          {
            "hints": [],
            "startTime": 1734618354396,
            "executionTime": 9,
            "source": [
              {
                "previousNode": "Start"
              }
            ],
            "executionStatus": "success",
            "data": {
              "main": [
                [
                  {
                    "json": {
                      "email": "test18354404@gmail.com"
                    },
                    "pairedItem": {
                      "item": 0
                    }
                  }
                ]
              ]
            }
          }
        ],
        "Mailchimp7": [
          {
            "hints": [],
            "startTime": 1734618354405,
            "executionTime": 325,
            "source": [
              {
                "previousNode": "Start"
              }
            ],
            "executionStatus": "success",
            "data": {
              "main": [
                [
                  {
                    "json": {
                      "category_id": "2adbc0d543",
                      "list_id": "eb9ad4be19",
                      "id": "928c597e2a",
                      "name": "QA",
                      "subscriber_count": "1",
                      "display_order": 1,
                      "_links": [
                        "json array"
                      ]
                    },
                    "pairedItem": {
                      "item": 0
                    }
                  }
                ]
              ]
            }
          }
        ],
        "Mailchimp8": [
          {
            "hints": [],
            "startTime": 1734618354730,
            "executionTime": 350,
            "source": [
              {
                "previousNode": "Start"
              }
            ],
            "executionStatus": "success",
            "data": {
              "main": [
                [
                  {
                    "json": {
                      "id": "6f13b9f38f",
                      "status": "save",
                      "settings": {
                        "object": true
                      },
                      "tracking": {
                        "object": true
                      }
                    },
                    "pairedItem": {
                      "item": 0
                    }
                  }
                ]
              ]
            }
          }
        ],
        "Mailchimp": [
          {
            "hints": [],
            "startTime": 1734618355080,
            "executionTime": 370,
            "source": [
              {
                "previousNode": "Mailchimp1"
              }
            ],
            "executionStatus": "success",
            "data": {
              "main": [
                [
                  {
                    "json": {
                      "id": "c81277605b129fdafaacede5ae34e07c",
                      "email_address": "nodeqa@n8n.io",
                      "unique_email_id": "cb7624ba4b",
                      "contact_id": "2f4ff7f445018adb50969f99df88dd9e",
                      "full_name": "node qa",
                      "web_id": 502612022,
                      "email_type": "html",
                      "status": "subscribed",
                      "consents_to_one_to_one_messaging": true,
                      "sms_phone_number": "",
                      "sms_subscription_status": "",
                      "sms_subscription_last_updated": "",
                      "merge_fields": {
                        "object": true
                      },
                      "interests": {
                        "object": true
                      },
                      "stats": {
                        "object": true
                      },
                      "ip_signup": "",
                      "timestamp_signup": "",
                      "ip_opt": "41.62.62.149",
                      "timestamp_opt": "2021-02-19T10:59:04+00:00",
                      "member_rating": 2,
                      "last_changed": "2024-12-19T14:21:21+00:00",
                      "language": "",
                      "vip": false,
                      "email_client": "",
                      "location": {
                        "object": true
                      },
                      "source": "Admin Add",
                      "tags_count": 0,
                      "tags": [
                        "json array"
                      ],
                      "list_id": "eb9ad4be19",
                      "_links": [
                        "json array"
                      ]
                    },
                    "pairedItem": {
                      "item": 0
                    }
                  }
                ]
              ]
            }
          }
        ],
        "Mailchimp3": [
          {
            "hints": [],
            "startTime": 1734618355450,
            "executionTime": 509,
            "source": [
              {
                "previousNode": "Function"
              }
            ],
            "executionStatus": "success",
            "data": {
              "main": [
                [
                  {
                    "json": {
                      "id": "d95227f7fd8eda1bf354b48b1d869a1a",
                      "email_address": "test18354404@gmail.com",
                      "unique_email_id": "b003e63532",
                      "contact_id": "2df336d66baf124368ad73cce823db6a",
                      "full_name": "",
                      "web_id": 606450574,
                      "email_type": "html",
                      "status": "subscribed",
                      "consents_to_one_to_one_messaging": true,
                      "sms_phone_number": "",
                      "sms_subscription_status": "",
                      "sms_subscription_last_updated": "",
                      "merge_fields": {
                        "object": true
                      },
                      "interests": {
                        "object": true
                      },
                      "stats": {
                        "object": true
                      },
                      "ip_signup": "",
                      "timestamp_signup": "",
                      "ip_opt": "84.145.44.63",
                      "timestamp_opt": "2024-12-19T14:25:55+00:00",
                      "member_rating": 2,
                      "last_changed": "2024-12-19T14:25:55+00:00",
                      "language": "",
                      "vip": false,
                      "email_client": "",
                      "location": {
                        "object": true
                      },
                      "source": "API - Generic",
                      "tags_count": 0,
                      "tags": [
                        "json array"
                      ],
                      "list_id": "eb9ad4be19",
                      "_links": [
                        "json array"
                      ]
                    },
                    "pairedItem": {
                      "item": 0
                    }
                  }
                ]
              ]
            }
          }
        ],
        "Mailchimp9": [
          {
            "hints": [],
            "startTime": 1734618355960,
            "executionTime": 344,
            "source": [
              {
                "previousNode": "Mailchimp8"
              }
            ],
            "executionStatus": "success",
            "data": {
              "main": [
                [
                  {
                    "json": {
                      "id": "6f13b9f38f",
                      "web_id": 4932290,
                      "type": "plaintext",
                      "create_time": "2021-06-04T09:15:43+00:00",
                      "archive_url": "http://eepurl.com/hAmnHn",
                      "long_archive_url": "https://us1.campaign-archive.com/?u=396affb9e515ed83edaecbba9&id=6f13b9f38f",
                      "status": "save",
                      "emails_sent": 0,
                      "send_time": "",
                      "content_type": "template",
                      "needs_block_refresh": false,
                      "resendable": false,
                      "recipients": {
                        "object": true
                      },
                      "settings": {
                        "object": true
                      },
                      "tracking": {
                        "object": true
                      },
                      "delivery_status": {
                        "object": true
                      },
                      "_links": [
                        "json array"
                      ]
                    },
                    "pairedItem": {
                      "item": 0
                    }
                  }
                ]
              ]
            }
          }
        ],
        "Mailchimp2": [
          {
            "hints": [],
            "startTime": 1734618356305,
            "executionTime": 347,
            "source": [
              {
                "previousNode": "Mailchimp"
              }
            ],
            "executionStatus": "success",
            "data": {
              "main": [
                [
                  {
                    "json": {
                      "id": "c81277605b129fdafaacede5ae34e07c",
                      "email_address": "nodeqa@n8n.io",
                      "unique_email_id": "cb7624ba4b",
                      "contact_id": "2f4ff7f445018adb50969f99df88dd9e",
                      "full_name": "node qa",
                      "web_id": 502612022,
                      "email_type": "html",
                      "status": "subscribed",
                      "consents_to_one_to_one_messaging": true,
                      "sms_phone_number": "",
                      "sms_subscription_status": "",
                      "sms_subscription_last_updated": "",
                      "merge_fields": {
                        "object": true
                      },
                      "interests": {
                        "object": true
                      },
                      "stats": {
                        "object": true
                      },
                      "ip_signup": "",
                      "timestamp_signup": "",
                      "ip_opt": "41.62.62.149",
                      "timestamp_opt": "2021-02-19T10:59:04+00:00",
                      "member_rating": 2,
                      "last_changed": "2024-12-19T14:21:21+00:00",
                      "language": "",
                      "vip": false,
                      "email_client": "",
                      "location": {
                        "object": true
                      },
                      "source": "Admin Add",
                      "tags_count": 0,
                      "tags": [
                        "json array"
                      ],
                      "list_id": "eb9ad4be19",
                      "_links": [
                        "json array"
                      ]
                    },
                    "pairedItem": {
                      "item": 0
                    }
                  }
                ]
              ]
            }
          }
        ],
        "Mailchimp4": [
          {
            "hints": [],
            "startTime": 1734618356652,
            "executionTime": 385,
            "source": [
              {
                "previousNode": "Mailchimp"
              }
            ],
            "executionStatus": "success",
            "data": {
              "main": [
                [
                  {
                    "json": {
                      "success": true
                    },
                    "pairedItem": {
                      "item": 0
                    }
                  }
                ]
              ]
            }
          }
        ],
        "Mailchimp6": [
          {
            "hints": [],
            "startTime": 1734618357038,
            "executionTime": 1752,
            "source": [
              {
                "previousNode": "Mailchimp3"
              }
            ],
            "executionStatus": "success",
            "data": {
              "main": [
                [
                  {
                    "json": {
                      "success": true
                    },
                    "pairedItem": {
                      "item": 0
                    }
                  }
                ]
              ]
            }
          }
        ],
        "Mailchimp10": [
          {
            "hints": [],
            "startTime": 1734618358790,
            "executionTime": 1933,
            "source": [
              {
                "previousNode": "Mailchimp9"
              }
            ],
            "executionStatus": "success",
            "data": {
              "main": [
                [
                  {
                    "json": {
                      "id": "e57f64e9e5",
                      "web_id": 11036749,
                      "type": "plaintext",
                      "create_time": "2024-12-19T14:25:59+00:00",
                      "archive_url": "http://eepurl.com/i6yS9w",
                      "long_archive_url": "https://us1.campaign-archive.com/?u=396affb9e515ed83edaecbba9&id=e57f64e9e5",
                      "status": "save",
                      "emails_sent": 0,
                      "send_time": "",
                      "content_type": "template",
                      "needs_block_refresh": false,
                      "resendable": false,
                      "recipients": {
                        "object": true
                      },
                      "settings": {
                        "object": true
                      },
                      "tracking": {
                        "object": true
                      },
                      "delivery_status": {
                        "object": true
                      },
                      "_links": [
                        "json array"
                      ]
                    },
                    "pairedItem": {
                      "item": 0
                    }
                  }
                ]
              ]
            }
          }
        ],
        "Mailchimp5": [
          {
            "hints": [],
            "startTime": 1734618360723,
            "executionTime": 381,
            "source": [
              {
                "previousNode": "Mailchimp4"
              }
            ],
            "executionStatus": "success",
            "data": {
              "main": [
                [
                  {
                    "json": {
                      "success": true
                    },
                    "pairedItem": {
                      "item": 0
                    }
                  }
                ]
              ]
            }
          }
        ],
        "Mailchimp11": [
          {
            "hints": [],
            "startTime": 1734618361105,
            "executionTime": 681,
            "source": [
              {
                "previousNode": "Mailchimp10"
              }
            ],
            "executionStatus": "success",
            "data": {
              "main": [
                [
                  {
                    "json": {
                      "success": true
                    },
                    "pairedItem": {
                      "item": 0
                    }
                  }
                ]
              ]
            }
          }
        ]
      },
      "lastNodeExecuted": "Mailchimp11"
    },
    "executionData": {
      "contextData": {},
      "nodeExecutionStack": [],
      "metadata": {},
      "waitingExecution": {},
      "waitingExecutionSource": {}
    }
  },
  "mode": "cli",
  "startedAt": "2024-12-19T14:25:52.520Z",
  "stoppedAt": "2024-12-19T14:26:01.787Z",
  "status": "running",
  "finished": true
}