{
  "data": {
    "startData": {},
    "resultData": {
      "runData": {
        "Start": [
          {
            "startTime": 1706635215708,
            "executionTime": 0,
            "source": [],
            "executionStatus": "success",
            "data": {
              "main": [
                [
                  {
                    "json": {},
                    "pairedItem": {
                      "item": 0
                    }
                  }
                ]
              ]
            }
          }
        ],
        "Gotify": [
          {
            "startTime": 1706635215708,
            "executionTime": 175,
            "source": [
              {
                "previousNode": "Start"
              }
            ],
            "executionStatus": "success",
            "data": {
              "main": [
                [
                  {
                    "json": {
                      "id": 1229,
                      "appid": 1,
                      "message": "Message content 1706635215713",
                      "title": "Title1706635215718",
                      "priority": 0,
                      "date": "2024-01-30T17:20:15.853020642Z"
                    },
                    "pairedItem": {
                      "item": 0
                    }
                  }
                ]
              ]
            }
          }
        ],
        "Gotify1": [
          {
            "startTime": 1706635215883,
            "executionTime": 54,
            "source": [
              {
                "previousNode": "Gotify"
              }
            ],
            "executionStatus": "success",
            "data": {
              "main": [
                [
                  {
                    "json": {
                      "id": 1229,
                      "appid": 1,
                      "message": "Message content 1706635215713",
                      "title": "Title1706635215718",
                      "priority": 0,
                      "date": "2024-01-30T17:20:15.853020642Z"
                    },
                    "pairedItem": {
                      "item": 0
                    }
                  }
                ]
              ]
            }
          }
        ],
        "Gotify2": [
          {
            "startTime": 1706635215938,
            "executionTime": 45,
            "source": [
              {
                "previousNode": "Gotify1"
              }
            ],
            "executionStatus": "success",
            "data": {
              "main": [
                [
                  {
                    "json": {
                      "success": true
                    },
                    "pairedItem": {
                      "item": 0
                    }
                  }
                ]
              ]
            }
          }
        ]
      },
      "lastNodeExecuted": "Gotify2"
    },
    "executionData": {
      "contextData": {},
      "nodeExecutionStack": [],
      "metadata": {},
      "waitingExecution": {},
      "waitingExecutionSource": {}
    }
  },
  "mode": "cli",
  "startedAt": "2024-01-30T17:20:15.708Z",
  "stoppedAt": "2024-01-30T17:20:15.983Z",
  "status": "running",
  "finished": true
}