{
  "data": {
    "startData": {},
    "resultData": {
      "runData": {
        "Start": [
          {
            "startTime": 1622541795754,
            "executionTime": 1,
            "data": {
              "main": [
                [
                  {
                    "json": {}
                  }
                ]
              ]
            }
          }
        ],
        "Keap": [
          {
            "startTime": 1622541795756,
            "executionTime": 942,
            "data": {
              "main": [
                [
                  {
                    "json": {
                      "email_opted_in": false,
                      "website": null,
                      "address": {
                        "line1": "",
                        "line2": "",
                        "locality": "",
                        "region": null,
                        "zip_code": null,
                        "zip_four": null,
                        "country_code": null
                      },
                      "email_address": null,
                      "company_name": "Company_2021-06-01T10:03:15.757Z",
                      "phone_number": {
                        "number": "",
                        "extension": null,
                        "type": null
                      },
                      "id": 106,
                      "email_status": "NonMarketable"
                    }
                  }
                ]
              ]
            }
          }
        ],
        "Keap1": [
          {
            "startTime": 1622541796699,
            "executionTime": 627,
            "data": {
              "main": [
                [
                  {
                    "json": {
                      "email_opted_in": false,
                      "website": null,
                      "address": {
                        "line1": "",
                        "line2": "",
                        "locality": "",
                        "region": null,
                        "zip_code": null,
                        "zip_four": null,
                        "country_code": null
                      },
                      "email_address": null,
                      "company_name": "Company_2021-05-17T14:59:20.273Z",
                      "phone_number": {
                        "number": "",
                        "extension": null,
                        "type": null
                      },
                      "id": 4,
                      "email_status": "NonMarketable"
                    }
                  }
                ]
              ]
            }
          }
        ],
        "Keap2": [
          {
            "startTime": 1622541797327,
            "executionTime": 880,
            "data": {
              "main": [
                [
                  {
                    "json": {
                      "email_addresses": [
                        {
                          "email": "fakeemail1622541797329@test.com",
                          "field": "EMAIL1"
                        }
                      ],
                      "email_opted_in": false,
                      "addresses": [],
                      "last_updated": "2021-06-01T10:03:18.012+0000",
                      "tag_ids": [],
                      "owner_id": null,
                      "date_created": "2021-06-01T10:03:18.012+0000",
                      "middle_name": null,
                      "given_name": "",
                      "ScoreValue": null,
                      "email_status": "NonMarketable",
                      "phone_numbers": [],
                      "last_updated_utc_millis": 1622541798012,
                      "company": {
                        "id": 106,
                        "company_name": "Company_2021-06-01T10:03:15.757Z"
                      },
                      "id": 108,
                      "family_name": ""
                    }
                  }
                ]
              ]
            }
          }
        ],
        "Keap6": [
          {
            "startTime": 1622541798208,
            "executionTime": 812,
            "data": {
              "main": [
                [
                  {
                    "json": {
                      "id": 40,
                      "title": "Note{Date.now()}}",
                      "body": "",
                      "type": null,
                      "contact_id": 108,
                      "user_id": 1,
                      "last_updated_by": {
                        "user_id": 1,
                        "given_name": "Qa",
                        "family_name": "Node"
                      },
                      "date_created": "2021-06-01T10:03:19Z",
                      "last_updated": "2021-06-01T10:03:19Z"
                    }
                  }
                ]
              ]
            }
          }
        ],
        "Keap11": [
          {
            "startTime": 1622541799020,
            "executionTime": 831,
            "data": {
              "main": [
                [
                  {
                    "json": {
                      "93": "SUCCESS"
                    }
                  }
                ]
              ]
            }
          }
        ],
        "Keap7": [
          {
            "startTime": 1622541799852,
            "executionTime": 765,
            "data": {
              "main": [
                [
                  {
                    "json": {
                      "id": 40,
                      "title": "Note{Date.now()}}",
                      "body": "",
                      "type": null,
                      "contact_id": 108,
                      "user_id": 1,
                      "last_updated_by": {
                        "user_id": 1,
                        "given_name": "Qa",
                        "family_name": "Node"
                      },
                      "date_created": "2021-06-01T10:03:19Z",
                      "last_updated": "2021-06-01T10:03:19Z"
                    }
                  }
                ]
              ]
            }
          }
        ],
        "Keap12": [
          {
            "startTime": 1622541800618,
            "executionTime": 793,
            "data": {
              "main": [
                [
                  {
                    "json": {
                      "tag": {
                        "id": 93,
                        "name": "New Customer",
                        "category": "Customer Tags"
                      },
                      "date_applied": "2021-06-01T10:03:20.000+0000"
                    }
                  }
                ]
              ]
            }
          }
        ],
        "Keap8": [
          {
            "startTime": 1622541801411,
            "executionTime": 753,
            "data": {
              "main": [
                [
                  {
                    "json": {
                      "id": 40,
                      "title": "Updated Title",
                      "body": "",
                      "type": null,
                      "contact_id": 108,
                      "user_id": 1,
                      "last_updated_by": {
                        "user_id": 1,
                        "given_name": "Qa",
                        "family_name": "Node"
                      },
                      "date_created": "2021-06-01T10:03:19Z",
                      "last_updated": "2021-06-01T10:03:22Z"
                    }
                  }
                ]
              ]
            }
          }
        ],
        "Keap13": [
          {
            "startTime": 1622541802164,
            "executionTime": 611,
            "data": {
              "main": [
                [
                  {
                    "json": {
                      "success": true
                    }
                  }
                ]
              ]
            }
          }
        ],
        "Keap9": [
          {
            "startTime": 1622541802775,
            "executionTime": 766,
            "data": {
              "main": [
                [
                  {
                    "json": {
                      "id": 8,
                      "title": "updated ttitle",
                      "body": "",
                      "type": "Email",
                      "contact_id": 34,
                      "user_id": 1,
                      "last_updated_by": {
                        "user_id": 1,
                        "given_name": "Qa",
                        "family_name": "Node"
                      },
                      "date_created": "2021-05-18T08:33:14Z",
                      "last_updated": "2021-05-18T08:34:13Z"
                    }
                  }
                ]
              ]
            }
          }
        ],
        "Keap10": [
          {
            "startTime": 1622541803541,
            "executionTime": 622,
            "data": {
              "main": [
                [
                  {
                    "json": {
                      "success": true
                    }
                  }
                ]
              ]
            }
          }
        ],
        "Keap3": [
          {
            "startTime": 1622541804164,
            "executionTime": 794,
            "data": {
              "main": [
                [
                  {
                    "json": {
                      "email_addresses": [
                        {
                          "email": "fakeemail1622541797329@test.com",
                          "field": "EMAIL1"
                        }
                      ],
                      "email_opted_in": false,
                      "addresses": [],
                      "last_updated": "2021-06-01T10:03:18.000+0000",
                      "tag_ids": [],
                      "owner_id": null,
                      "date_created": "2021-06-01T10:03:18.000+0000",
                      "middle_name": null,
                      "given_name": "",
                      "ScoreValue": "1",
                      "email_status": "NonMarketable",
                      "phone_numbers": [],
                      "last_updated_utc_millis": 1622541798012,
                      "company": {
                        "id": 106,
                        "company_name": "Company_2021-06-01T10:03:15.757Z"
                      },
                      "id": 108,
                      "family_name": ""
                    }
                  }
                ]
              ]
            }
          }
        ],
        "Keap4": [
          {
            "startTime": 1622541804959,
            "executionTime": 761,
            "data": {
              "main": [
                [
                  {
                    "json": {
                      "email_addresses": [
                        {
                          "email": "fakeemail1622541797329@test.com",
                          "field": "EMAIL1"
                        }
                      ],
                      "email_opted_in": false,
                      "addresses": [],
                      "last_updated": "2021-06-01T10:03:18.000+0000",
                      "tag_ids": [],
                      "owner_id": null,
                      "date_created": "2021-06-01T10:03:18.000+0000",
                      "middle_name": null,
                      "given_name": "",
                      "ScoreValue": null,
                      "email_status": "NonMarketable",
                      "phone_numbers": [],
                      "last_updated_utc_millis": 1622541798012,
                      "company": {
                        "id": 106,
                        "company_name": "Company_2021-06-01T10:03:15.757Z"
                      },
                      "id": 108,
                      "family_name": ""
                    }
                  }
                ]
              ]
            }
          }
        ],
        "Keap5": [
          {
            "startTime": 1622541805722,
            "executionTime": 850,
            "data": {
              "main": [
                [
                  {
                    "json": {
                      "success": true
                    }
                  }
                ]
              ]
            }
          }
        ]
      },
      "lastNodeExecuted": "Keap5"
    },
    "executionData": {
      "contextData": {},
      "nodeExecutionStack": [],
      "waitingExecution": {}
    }
  },
  "mode": "cli",
  "startedAt": "2021-06-01T10:03:15.750Z",
  "stoppedAt": "2021-06-01T10:03:26.572Z",
  "finished": true
}