{
  "data": {
    "startData": {},
    "resultData": {
      "runData": {
        "Start": [
          {
            "startTime": 1706635225473,
            "executionTime": 0,
            "source": [],
            "executionStatus": "success",
            "data": {
              "main": [
                [
                  {
                    "json": {},
                    "pairedItem": {
                      "item": 0
                    }
                  }
                ]
              ]
            }
          }
        ],
        "Delete existing dir": [
          {
            "startTime": 1706635225473,
            "executionTime": 6,
            "source": [
              {
                "previousNode": "Start"
              }
            ],
            "executionStatus": "success",
            "data": {
              "main": [
                [
                  {
                    "json": {
                      "exitCode": 0,
                      "stderr": "",
                      "stdout": ""
                    },
                    "pairedItem": {
                      "item": 0
                    }
                  }
                ]
              ]
            }
          }
        ],
        "Git": [
          {
            "startTime": 1706635225479,
            "executionTime": 732,
            "source": [
              {
                "previousNode": "Delete existing dir"
              }
            ],
            "executionStatus": "success",
            "data": {
              "main": [
                [
                  {
                    "json": {
                      "success": true
                    },
                    "pairedItem": {
                      "item": 0
                    }
                  }
                ]
              ]
            }
          }
        ],
        "Git1": [
          {
            "startTime": 1706635226211,
            "executionTime": 4,
            "source": [
              {
                "previousNode": "Git"
              }
            ],
            "executionStatus": "success",
            "data": {
              "main": [
                [
                  {
                    "json": {
                      "_file": ".git/config"
                    },
                    "pairedItem": {
                      "item": 0
                    }
                  }
                ]
              ]
            }
          }
        ],
        "Git2": [
          {
            "startTime": 1706635226215,
            "executionTime": 53,
            "source": [
              {
                "previousNode": "Git1"
              }
            ],
            "executionStatus": "success",
            "data": {
              "main": [
                [
                  {
                    "json": {
                      "success": true
                    },
                    "pairedItem": {
                      "item": 0
                    }
                  }
                ]
              ]
            }
          }
        ],
        "Git7": [
          {
            "startTime": 1706635226268,
            "executionTime": 55,
            "source": [
              {
                "previousNode": "Git2"
              }
            ],
            "executionStatus": "success",
            "data": {
              "main": [
                [
                  {
                    "json": {
                      "success": true
                    },
                    "pairedItem": {
                      "item": 0
                    }
                  }
                ]
              ]
            }
          }
        ],
        "Add file to dir": [
          {
            "startTime": 1706635226324,
            "executionTime": 15,
            "source": [
              {
                "previousNode": "Git7"
              }
            ],
            "executionStatus": "success",
            "data": {
              "main": [
                [
                  {
                    "json": {
                      "exitCode": 0,
                      "stderr": "",
                      "stdout": ""
                    },
                    "pairedItem": {
                      "item": 0
                    }
                  }
                ]
              ]
            }
          }
        ],
        "Git3": [
          {
            "startTime": 1706635226340,
            "executionTime": 57,
            "source": [
              {
                "previousNode": "Add file to dir"
              }
            ],
            "executionStatus": "success",
            "data": {
              "main": [
                [
                  {
                    "json": {
                      "success": true
                    },
                    "pairedItem": {
                      "item": 0
                    }
                  }
                ]
              ]
            }
          }
        ],
        "Git4": [
          {
            "startTime": 1706635226398,
            "executionTime": 8,
            "source": [
              {
                "previousNode": "Git3"
              }
            ],
            "executionStatus": "success",
            "data": {
              "main": [
                [
                  {
                    "json": {
                      "not_added": [
                        "json array"
                      ],
                      "conflicted": [
                        "json array"
                      ],
                      "created": [
                        "json array"
                      ],
                      "deleted": [
                        "json array"
                      ],
                      "modified": [
                        "json array"
                      ],
                      "renamed": [
                        "json array"
                      ],
                      "files": [
                        "json array"
                      ],
                      "staged": [
                        "json array"
                      ],
                      "ahead": 0,
                      "behind": 0,
                      "current": "main",
                      "tracking": "origin/main",
                      "detached": false
                    },
                    "pairedItem": {
                      "item": 0
                    }
                  }
                ]
              ]
            }
          }
        ],
        "Git5": [
          {
            "startTime": 1706635226406,
            "executionTime": 18,
            "source": [
              {
                "previousNode": "Git4"
              }
            ],
            "executionStatus": "success",
            "data": {
              "main": [
                [
                  {
                    "json": {
                      "success": true
                    },
                    "pairedItem": {
                      "item": 0
                    }
                  }
                ]
              ]
            }
          }
        ],
        "Git6": [
          {
            "startTime": 1706635226424,
            "executionTime": 9,
            "source": [
              {
                "previousNode": "Git5"
              }
            ],
            "executionStatus": "success",
            "data": {
              "main": [
                [
                  {
                    "json": {
                      "hash": "b21851b2cde5efe212149d1cb99bf6d85c0ce129",
                      "date": "2024-01-30T18:20:26+01:00",
                      "message": "GitNode commit Tue, 30 Jan 2024 17:20:26 GMT",
                      "refs": "HEAD -> main",
                      "body": "",
                      "author_name": "nodemationqa",
                      "author_email": "nodeqa@n8n.io"
                    },
                    "pairedItem": {
                      "item": 0
                    }
                  }
                ]
              ]
            }
          }
        ],
        "Git8": [
          {
            "startTime": 1706635226434,
            "executionTime": 60,
            "source": [
              {
                "previousNode": "Git6"
              }
            ],
            "executionStatus": "success",
            "data": {
              "main": [
                [
                  {
                    "json": {
                      "success": true
                    },
                    "pairedItem": {
                      "item": 0
                    }
                  }
                ]
              ]
            }
          }
        ],
        "Git9": [
          {
            "startTime": 1706635226494,
            "executionTime": 0,
            "source": [
              {
                "previousNode": "Git8"
              }
            ],
            "executionStatus": "success",
            "data": {
              "main": [
                [
                  {
                    "json": {
                      "success": true
                    },
                    "pairedItem": {
                      "item": 0
                    }
                  }
                ]
              ]
            }
          }
        ],
        "Git10": [
          {
            "startTime": 1706635226495,
            "executionTime": 0,
            "source": [
              {
                "previousNode": "Git9"
              }
            ],
            "executionStatus": "success",
            "data": {
              "main": [
                [
                  {
                    "json": {
                      "success": true
                    },
                    "pairedItem": {
                      "item": 0
                    }
                  }
                ]
              ]
            }
          }
        ],
        "Git11": [
          {
            "startTime": 1706635226495,
            "executionTime": 0,
            "source": [
              {
                "previousNode": "Git10"
              }
            ],
            "executionStatus": "success",
            "data": {
              "main": [
                [
                  {
                    "json": {
                      "success": true
                    },
                    "pairedItem": {
                      "item": 0
                    }
                  }
                ]
              ]
            }
          }
        ],
        "Git12": [
          {
            "startTime": 1706635226495,
            "executionTime": 410,
            "source": [
              {
                "previousNode": "Git11"
              }
            ],
            "executionStatus": "success",
            "data": {
              "main": [
                [
                  {
                    "json": {
                      "success": true
                    },
                    "pairedItem": {
                      "item": 0
                    }
                  }
                ]
              ]
            }
          }
        ],
        "Git13": [
          {
            "startTime": 1706635226906,
            "executionTime": 0,
            "source": [
              {
                "previousNode": "Git12"
              }
            ],
            "executionStatus": "success",
            "data": {
              "main": [
                [
                  {
                    "json": {
                      "success": true
                    },
                    "pairedItem": {
                      "item": 0
                    }
                  }
                ]
              ]
            }
          }
        ]
      },
      "lastNodeExecuted": "Git13"
    },
    "executionData": {
      "contextData": {},
      "nodeExecutionStack": [],
      "metadata": {},
      "waitingExecution": {},
      "waitingExecutionSource": {}
    }
  },
  "mode": "cli",
  "startedAt": "2024-01-30T17:20:25.472Z",
  "stoppedAt": "2024-01-30T17:20:26.906Z",
  "status": "running",
  "finished": true
}