{
  "data": {
    "startData": {},
    "resultData": {
      "runData": {
        "Start": [
          {
            "startTime": 1676026064478,
            "executionTime": 0,
            "source": [],
            "data": {
              "main": [
                [
                  {
                    "json": {},
                    "pairedItem": {
                      "item": 0
                    }
                  }
                ]
              ]
            }
          }
        ],
        "ActiveCampaign": [
          {
            "startTime": 1676026064479,
            "executionTime": 633,
            "source": [
              {
                "previousNode": "Start"
              }
            ],
            "data": {
              "main": [
                [
                  {
                    "json": {
                      "connection": {
                        "object": true
                      }
                    },
                    "pairedItem": {
                      "item": 0
                    }
                  }
                ]
              ]
            }
          }
        ],
        "ActiveCampaign5": [
          {
            "startTime": 1676026065113,
            "executionTime": 419,
            "source": [
              {
                "previousNode": "Start"
              }
            ],
            "data": {
              "main": [
                [
                  {
                    "json": {
                      "email": "fake1676026065118@gmail.com",
                      "email_empty": false,
                      "cdate": "2023-02-10T04:47:45-06:00",
                      "udate": "2023-02-10T04:47:45-06:00",
                      "orgid": "",
                      "orgname": "",
                      "links": {
                        "object": true
                      },
                      "hash": "a1a0a6e4da6ffad0d7506efcd6fa6614",
                      "id": "1185",
                      "organization": ""
                    },
                    "pairedItem": {
                      "item": 0
                    }
                  }
                ]
              ]
            }
          }
        ],
        "ActiveCampaign8": [
          {
            "startTime": 1676026065532,
            "executionTime": 301,
            "source": [
              {
                "previousNode": "Start"
              }
            ],
            "data": {
              "main": [
                [
                  {
                    "json": {
                      "stringid": "testlist",
                      "userid": "1",
                      "name": "TestList",
                      "cdate": "2021-03-02T10:30:17-06:00",
                      "p_use_tracking": "1",
                      "p_use_analytics_read": "0",
                      "p_use_analytics_link": "0",
                      "p_use_twitter": "0",
                      "p_use_facebook": "0",
                      "p_embed_image": "1",
                      "p_use_captcha": "1",
                      "send_last_broadcast": "0",
                      "private": "0",
                      "analytics_domains": {
                        "object": true
                      },
                      "analytics_source": "",
                      "analytics_ua": "",
                      "twitter_token": "",
                      "twitter_token_secret": "",
                      "facebook_session": {
                        "object": true
                      },
                      "carboncopy": {
                        "object": true
                      },
                      "subscription_notify": {
                        "object": true
                      },
                      "unsubscription_notify": {
                        "object": true
                      },
                      "require_name": "0",
                      "get_unsubscribe_reason": "0",
                      "to_name": "Subscriber",
                      "optinoptout": "1",
                      "sender_name": "",
                      "sender_addr1": "",
                      "sender_addr2": "",
                      "sender_city": "",
                      "sender_state": "",
                      "sender_zip": "",
                      "sender_country": "",
                      "sender_phone": "",
                      "sender_url": "https://n8n1612344344.activehosted.com",
                      "sender_reminder": "You are receiving these emails because you are subscribed to our updates.",
                      "fulladdress": "",
                      "optinmessageid": "0",
                      "optoutconf": "0",
                      "deletestamp": {
                        "object": true
                      },
                      "udate": {
                        "object": true
                      },
                      "created_timestamp": "2021-03-02 10:30:17",
                      "updated_timestamp": "2021-03-02 10:30:17",
                      "created_by": {
                        "object": true
                      },
                      "updated_by": {
                        "object": true
                      },
                      "links": {
                        "object": true
                      },
                      "id": "1",
                      "user": "1"
                    },
                    "pairedItem": {
                      "item": 0
                    }
                  }
                ]
              ]
            }
          }
        ],
        "ActiveCampaign9": [
          {
            "startTime": 1676026065833,
            "executionTime": 285,
            "source": [
              {
                "previousNode": "Start"
              }
            ],
            "data": {
              "main": [
                [
                  {
                    "json": {
                      "tag": "Tag1676026065834",
                      "tagType": "contact",
                      "cdate": "2023-02-10T04:47:46-06:00",
                      "links": {
                        "object": true
                      },
                      "id": "234"
                    },
                    "pairedItem": {
                      "item": 0
                    }
                  }
                ]
              ]
            }
          }
        ],
        "ActiveCampaign1": [
          {
            "startTime": 1676026066118,
            "executionTime": 325,
            "source": [
              {
                "previousNode": "ActiveCampaign"
              }
            ],
            "data": {
              "main": [
                [
                  {
                    "json": {
                      "connection": {
                        "object": true
                      }
                    },
                    "pairedItem": {
                      "item": 0
                    }
                  }
                ]
              ]
            }
          }
        ],
        "ActiveCampaign7": [
          {
            "startTime": 1676026066443,
            "executionTime": 624,
            "source": [
              {
                "previousNode": "ActiveCampaign5"
              }
            ],
            "data": {
              "main": [
                [
                  {
                    "json": {
                      "contacts": [
                        "json array"
                      ],
                      "dealGroups": [
                        "json array"
                      ],
                      "dealStages": [
                        "json array"
                      ],
                      "deal": {
                        "object": true
                      }
                    },
                    "pairedItem": {
                      "item": 0
                    }
                  }
                ]
              ]
            }
          }
        ],
        "ActiveCampaign10": [
          {
            "startTime": 1676026067067,
            "executionTime": 288,
            "source": [
              {
                "previousNode": "ActiveCampaign9"
              }
            ],
            "data": {
              "main": [
                [
                  {
                    "json": {
                      "tagType": "contact",
                      "tag": "Tag1676026065834",
                      "description": "",
                      "subscriber_count": "0",
                      "cdate": "2023-02-10T04:47:46-06:00",
                      "created_timestamp": "2023-02-10 04:47:46",
                      "updated_timestamp": "2023-02-10 04:47:46",
                      "created_by": {
                        "object": true
                      },
                      "updated_by": {
                        "object": true
                      },
                      "links": {
                        "object": true
                      },
                      "id": "234"
                    },
                    "pairedItem": {
                      "item": 0
                    }
                  }
                ]
              ]
            }
          }
        ],
        "ActiveCampaign2": [
          {
            "startTime": 1676026067355,
            "executionTime": 548,
            "source": [
              {
                "previousNode": "ActiveCampaign1"
              }
            ],
            "data": {
              "main": [
                [
                  {
                    "json": {
                      "connection": {
                        "object": true
                      }
                    },
                    "pairedItem": {
                      "item": 0
                    }
                  }
                ]
              ]
            }
          }
        ],
        "ActiveCampaign14": [
          {
            "startTime": 1676026067903,
            "executionTime": 375,
            "source": [
              {
                "previousNode": "ActiveCampaign7"
              }
            ],
            "data": {
              "main": [
                [
                  {
                    "json": {
                      "dealStages": [
                        "json array"
                      ],
                      "deal": {
                        "object": true
                      }
                    },
                    "pairedItem": {
                      "item": 0
                    }
                  }
                ]
              ]
            }
          }
        ],
        "ActiveCampaign11": [
          {
            "startTime": 1676026068279,
            "executionTime": 310,
            "source": [
              {
                "previousNode": "ActiveCampaign10"
              }
            ],
            "data": {
              "main": [
                [
                  {
                    "json": {
                      "tag": {
                        "object": true
                      }
                    },
                    "pairedItem": {
                      "item": 0
                    }
                  }
                ]
              ]
            }
          }
        ],
        "ActiveCampaign3": [
          {
            "startTime": 1676026068590,
            "executionTime": 282,
            "source": [
              {
                "previousNode": "ActiveCampaign2"
              }
            ],
            "data": {
              "main": [
                [
                  {
                    "json": {
                      "service": "n8n",
                      "externalid": "1621002648800",
                      "name": "Name1621002648800",
                      "isInternal": "0",
                      "connectionType": "ecommerce",
                      "status": "1",
                      "syncStatus": "0",
                      "sync_request_time": {
                        "object": true
                      },
                      "sync_start_time": {
                        "object": true
                      },
                      "lastSync": {
                        "object": true
                      },
                      "logoUrl": "https://n8n.io/_nuxt/img/df5be1c.png",
                      "linkUrl": "https://n8n.io/",
                      "credentialExpiration": {
                        "object": true
                      },
                      "cdate": "2021-05-14T09:31:09-05:00",
                      "udate": "2021-05-14T09:31:09-05:00",
                      "disconnectDate": {
                        "object": true
                      },
                      "links": {
                        "object": true
                      },
                      "id": "92",
                      "serviceName": "n8n"
                    },
                    "pairedItem": {
                      "item": 0
                    }
                  }
                ]
              ]
            }
          }
        ],
        "ActiveCampaign15": [
          {
            "startTime": 1676026068872,
            "executionTime": 258,
            "source": [
              {
                "previousNode": "ActiveCampaign14"
              }
            ],
            "data": {
              "main": [
                [
                  {
                    "json": {
                      "deal": {
                        "object": true
                      }
                    },
                    "pairedItem": {
                      "item": 0
                    }
                  }
                ]
              ]
            }
          }
        ],
        "ActiveCampaign12": [
          {
            "startTime": 1676026069130,
            "executionTime": 406,
            "source": [
              {
                "previousNode": "ActiveCampaign11"
              }
            ],
            "data": {
              "main": [
                [
                  {
                    "json": {
                      "tagType": "contact",
                      "tag": "TestTag",
                      "description": "",
                      "subscriber_count": "1",
                      "cdate": "2021-03-02T10:29:14-06:00",
                      "created_timestamp": "2021-03-02 10:29:14",
                      "updated_timestamp": "2023-02-10 04:47:49",
                      "created_by": {
                        "object": true
                      },
                      "updated_by": {
                        "object": true
                      },
                      "links": {
                        "object": true
                      },
                      "id": "1"
                    },
                    "pairedItem": {
                      "item": 0
                    }
                  }
                ]
              ]
            }
          }
        ],
        "ActiveCampaign4": [
          {
            "startTime": 1676026069536,
            "executionTime": 423,
            "source": [
              {
                "previousNode": "ActiveCampaign3"
              }
            ],
            "data": {
              "main": [
                [
                  {
                    "json": {},
                    "pairedItem": {
                      "item": 0
                    }
                  }
                ]
              ]
            }
          }
        ],
        "ActiveCampaign16": [
          {
            "startTime": 1676026069959,
            "executionTime": 334,
            "source": [
              {
                "previousNode": "ActiveCampaign15"
              }
            ],
            "data": {
              "main": [
                [
                  {
                    "json": {
                      "deals": [
                        "json array"
                      ],
                      "note": {
                        "object": true
                      }
                    },
                    "pairedItem": {
                      "item": 0
                    }
                  }
                ]
              ]
            }
          }
        ],
        "ActiveCampaign13": [
          {
            "startTime": 1676026070294,
            "executionTime": 274,
            "source": [
              {
                "previousNode": "ActiveCampaign12"
              }
            ],
            "data": {
              "main": [
                [
                  {
                    "json": {},
                    "pairedItem": {
                      "item": 0
                    }
                  }
                ]
              ]
            }
          }
        ],
        "ActiveCampaign17": [
          {
            "startTime": 1676026070568,
            "executionTime": 314,
            "source": [
              {
                "previousNode": "ActiveCampaign16"
              }
            ],
            "data": {
              "main": [
                [
                  {
                    "json": {
                      "users": [
                        "json array"
                      ],
                      "deals": [
                        "json array"
                      ],
                      "note": {
                        "object": true
                      }
                    },
                    "pairedItem": {
                      "item": 0
                    }
                  }
                ]
              ]
            }
          }
        ],
        "ActiveCampaign18": [
          {
            "startTime": 1676026070882,
            "executionTime": 272,
            "source": [
              {
                "previousNode": "ActiveCampaign17"
              }
            ],
            "data": {
              "main": [
                [
                  {
                    "json": {
                      "hash": "92900823",
                      "owner": "1",
                      "contact": "254",
                      "organization": {
                        "object": true
                      },
                      "group": "1",
                      "stage": "1",
                      "title": "Title1622470457097",
                      "description": "",
                      "percent": "0",
                      "cdate": "2021-05-31T09:14:17-05:00",
                      "mdate": "2021-05-31T09:14:18-05:00",
                      "nextdate": {
                        "object": true
                      },
                      "nexttaskid": "0",
                      "value": "201",
                      "currency": "usd",
                      "winProbability": {
                        "object": true
                      },
                      "winProbabilityMdate": {
                        "object": true
                      },
                      "status": "0",
                      "activitycount": "3",
                      "nextdealid": "82",
                      "edate": "0000-00-00 00:00:00",
                      "links": {
                        "object": true
                      },
                      "id": "82",
                      "isDisabled": false,
                      "nextTask": {
                        "object": true
                      },
                      "account": {
                        "object": true
                      },
                      "customerAccount": {
                        "object": true
                      }
                    },
                    "pairedItem": {
                      "item": 0
                    }
                  }
                ]
              ]
            }
          }
        ],
        "ActiveCampaign19": [
          {
            "startTime": 1676026071154,
            "executionTime": 424,
            "source": [
              {
                "previousNode": "ActiveCampaign18"
              }
            ],
            "data": {
              "main": [
                [
                  {
                    "json": {},
                    "pairedItem": {
                      "item": 0
                    }
                  }
                ]
              ]
            }
          }
        ],
        "ActiveCampaign6": [
          {
            "startTime": 1676026071578,
            "executionTime": 390,
            "source": [
              {
                "previousNode": "ActiveCampaign19"
              }
            ],
            "data": {
              "main": [
                [
                  {
                    "json": {},
                    "pairedItem": {
                      "item": 0
                    }
                  }
                ]
              ]
            }
          }
        ]
      },
      "lastNodeExecuted": "ActiveCampaign6"
    },
    "executionData": {
      "contextData": {},
      "nodeExecutionStack": [],
      "waitingExecution": {},
      "waitingExecutionSource": {}
    }
  },
  "mode": "cli",
  "startedAt": "2023-02-10T10:47:44.464Z",
  "stoppedAt": "2023-02-10T10:47:51.969Z",
  "finished": true
}