{
  "data": {
    "startData": {},
    "resultData": {
      "runData": {
        "Start": [
          {
            "startTime": 1676027873291,
            "executionTime": 3,
            "source": [],
            "data": {
              "main": [
                [
                  {
                    "json": {},
                    "pairedItem": {
                      "item": 0
                    }
                  }
                ]
              ]
            }
          }
        ],
        "MessageBird": [
          {
            "startTime": 1676027873295,
            "executionTime": 212,
            "source": [
              {
                "previousNode": "Start"
              }
            ],
            "data": {
              "main": [
                [
                  {
                    "json": {
                      "payment": "prepaid",
                      "type": "dollars",
                      "amount": 0
                    },
                    "pairedItem": {
                      "item": 0
                    }
                  }
                ]
              ]
            }
          }
        ],
        "MessageBird1": [
          {
            "startTime": 1676027873507,
            "executionTime": 159,
            "source": [
              {
                "previousNode": "Start"
              }
            ],
            "data": {
              "main": [
                [
                  {
                    "json": {
                      "id": "a96675f325524808b05afdde9c00b93d",
                      "href": "https://rest.messagebird.com/messages/a96675f325524808b05afdde9c00b93d",
                      "direction": "mt",
                      "type": "sms",
                      "originator": "4930270504079",
                      "body": "TestMessage",
                      "reference": {
                        "object": true
                      },
                      "validity": {
                        "object": true
                      },
                      "gateway": 10,
                      "typeDetails": {
                        "object": true
                      },
                      "datacoding": "plain",
                      "mclass": 1,
                      "scheduledDatetime": {
                        "object": true
                      },
                      "createdDatetime": "2023-02-10T11:17:53+00:00",
                      "recipients": {
                        "object": true
                      }
                    },
                    "pairedItem": {
                      "item": 0
                    }
                  }
                ]
              ]
            }
          }
        ]
      },
      "lastNodeExecuted": "MessageBird1"
    },
    "executionData": {
      "contextData": {},
      "nodeExecutionStack": [],
      "waitingExecution": {},
      "waitingExecutionSource": {}
    }
  },
  "mode": "cli",
  "startedAt": "2023-02-10T11:17:53.285Z",
  "stoppedAt": "2023-02-10T11:17:53.666Z",
  "finished": true
}